mev_boost_py/proposer_payload.py
mev_boost_py-0.1.2.dist-info/METADATA
mev_boost_py-0.1.2.dist-info/WHEEL
mev_boost_py-0.1.2.dist-info/RECORD
