Metadata-Version: 2.3
Name: mev-boost-py
Version: 0.1.2
Summary: mev-boost python wrapper to access mev-boost data
Author-email: Evan-Kim2028 <ekcopersonal@gmail.com>
Requires-Python: >=3.8
Requires-Dist: polars>=1.6.0
Requires-Dist: requests>=2.32.3
